mkdocs_idm/README.md
mkdocs_idm/__init__.py
mkdocs_idm/glossary.md
mkdocs_idm/index.md
mkdocs_idm/install.md
mkdocs_idm/mkdocs_theme.yml
mkdocs_idm/requirements.txt
mkdocs_idm/whatsnew.md
mkdocs_idm/yaml_utils.py
mkdocs_idm/customization/javascripts/mathjax.js
mkdocs_idm/customization/overrides/partials/copyright.html
mkdocs_idm/images/IDM_white.png
mkdocs_idm/images/favicon-starsim.ico
mkdocs_idm/images/favicon.ico
mkdocs_idm/images/idm-logo-transparent.png
mkdocs_idm/images/starsim-logo.png
mkdocs_idm-1.3.1.dist-info/licenses/LICENSE
mkdocs_idm-1.3.1.dist-info/METADATA
mkdocs_idm-1.3.1.dist-info/WHEEL
mkdocs_idm-1.3.1.dist-info/entry_points.txt
mkdocs_idm-1.3.1.dist-info/top_level.txt
mkdocs_idm-1.3.1.dist-info/RECORD
