Metadata-Version: 2.4
Name: mkdocs-idm
Version: 1.3.1
Summary: IDM's custom MkDocs theme based on Material with enhanced features
License: MIT
Project-URL: Homepage, https://github.com/InstituteforDiseaseModeling/mkdocs-idm-theme
Project-URL: Documentation, https://docs.idmod.org
Project-URL: Repository, https://github.com/InstituteforDiseaseModeling/mkdocs-idm-theme
Project-URL: Bug Tracker, https://github.com/InstituteforDiseaseModeling/mkdocs-idm-theme/issues
Keywords: mkdocs,theme,material,documentation,idm,jupyter,api
Classifier: Development Status :: 4 - Beta
Classifier: Intended Audience :: Developers
Classifier: Intended Audience :: Science/Research
Classifier: License :: OSI Approved :: MIT License
Classifier: Programming Language :: Python :: 3
Classifier: Programming Language :: Python :: 3.8
Classifier: Programming Language :: Python :: 3.9
Classifier: Programming Language :: Python :: 3.10
Classifier: Programming Language :: Python :: 3.11
Classifier: Programming Language :: Python :: 3.12
Classifier: Topic :: Documentation
Classifier: Topic :: Software Development :: Documentation
Classifier: Topic :: Scientific/Engineering
Requires-Python: >=3.8
License-File: LICENSE
Requires-Dist: tomli>=1.2.0
Requires-Dist: mkdocs-material
Requires-Dist: mkdocs-include-markdown-plugin
Requires-Dist: mkdocs-autorefs
Requires-Dist: mkdocs-autoapi
Requires-Dist: mkdocs-section-index
Requires-Dist: python-markdown-math
Requires-Dist: pymdown-extensions>=10.0
Requires-Dist: mkdocs-jupyter
Requires-Dist: mkdocstrings-python
Requires-Dist: PyYAML>=6.0
Provides-Extra: dev
Requires-Dist: build; extra == "dev"
Requires-Dist: twine; extra == "dev"
Requires-Dist: pytest; extra == "dev"
Provides-Extra: example
Requires-Dist: starsim; extra == "example"
Dynamic: license-file
